mathsnip/__init__.py
mathsnip/__main__.py
mathsnip/mathsnip.py
mathsnip/service.py
mathsnip/logx/__init__.py
mathsnip/logx/colored_handler.py
mathsnip/logx/logging.yaml
mathsnip/logx/setup_logging.py
mathsnip-0.0.7.dist-info/METADATA
mathsnip-0.0.7.dist-info/WHEEL
mathsnip-0.0.7.dist-info/entry_points.txt
mathsnip-0.0.7.dist-info/top_level.txt
mathsnip-0.0.7.dist-info/RECORD
