Metadata-Version: 2.1
Name: mathsnip
Version: 0.0.7
Summary: this is a description
Home-page: https://github.com/zk4/mathsnip
Download-URL: https://github.com/zk4/mathsnip/archive/master.zip
Author: zk
Author-email: liuzq7@gmail.com
License: BSD
Keywords: best practice for python project
Classifier: Development Status :: 5 - Production/Stable
Classifier: Environment :: Console
Requires-Python: >3.0.0
Requires-Dist: Pillow (==9.5.0)
Requires-Dist: PySimpleGUI (==4.60.5)
Requires-Dist: pywildcard (==1.0.10)
Requires-Dist: requests (==2.31.0)
